src/__init__.py
src/config.py
src/console.py
src/exceptions.py
src/main.py
src/utils.py
src/cli/__init__.py
src/cli/app.py
src/cli/commands.py
src/cli/formatting.py
src/cli/utils.py
src/placeholder/__init__.py
src/placeholder/cli.py
src/placeholder/config.py
src/placeholder/exceptions.py
src/placeholder/main.py
src/placeholder/utils.py
src/server/__init__.py
src/server/main.py
src/server/query_processor.py
src/server/server_config.py
src/server/server_utils.py
src/server/state.py
src/server/utils.py
src/server/routers/__init__.py
src/server/routers/dynamic.py
src/server/routers/index.py
src/server/routers/terminal.py
src/server/templates/api.jinja
src/server/templates/base.jinja
src/server/templates/git.jinja
src/server/templates/index.jinja
src/server/templates/components/footer.jinja
src/server/templates/components/git_form.jinja
src/server/templates/components/navbar.jinja
src/server/templates/components/result.jinja
src/static/apple-touch-icon.png
src/static/favicon-64.png
src/static/favicon.ico
src/static/favicon.svg
src/static/og-image.png
src/static/robots.txt
src/static/js/utils.js
terminus_cli-0.1.0.dist-info/METADATA
terminus_cli-0.1.0.dist-info/WHEEL
terminus_cli-0.1.0.dist-info/entry_points.txt
terminus_cli-0.1.0.dist-info/licenses/LICENSE
terminus_cli-0.1.0.dist-info/RECORD
