Metadata-Version: 2.4
Name: terminus-cli
Version: 0.1.0
Summary: Access terminals from your computer, in your browser.
Project-URL: homepage, https://terminus.run
Project-URL: github, https://github.com/atyrode/terminus
Author-email: Alex TYRODE <alex.tyrode@outlook.fr>
License: MIT License
License-File: LICENSE
Classifier: Development Status :: 3 - Alpha
Classifier: Intended Audience :: Developers
Classifier: License :: OSI Approved :: MIT License
Classifier: Programming Language :: Python :: 3.10
Classifier: Programming Language :: Python :: 3.11
Classifier: Programming Language :: Python :: 3.12
Classifier: Programming Language :: Python :: 3.13
Requires-Python: >=3.10
Requires-Dist: click>=8.0.0
Requires-Dist: fastapi[standard]
Requires-Dist: httpx>=0.24.0
Requires-Dist: python-dotenv
Requires-Dist: python-multipart>=0.0.5
Requires-Dist: rich>=13.7.0
Requires-Dist: tomli>=2.0.1; python_version < '3.11'
Requires-Dist: websockets>=10.0
